opsmate/__init__.py
opsmate/apiserver/__init__.py
opsmate/apiserver/apiserver.py
opsmate/cli/__init__.py
opsmate/cli/cli.py
opsmate/config/__init__.py
opsmate/contexts/__init__.py
opsmate/contexts/cli.py
opsmate/contexts/cli_lite.py
opsmate/contexts/k8s.py
opsmate/contexts/terraform.py
opsmate/dbq/__init__.py
opsmate/dbq/dbq.py
opsmate/dbqapp/app.py
opsmate/dino/__init__.py
opsmate/dino/context.py
opsmate/dino/dino.py
opsmate/dino/react.py
opsmate/dino/tools.py
opsmate/dino/types.py
opsmate/dino/utils.py
opsmate/dino/provider/__init__.py
opsmate/dino/provider/anthropic.py
opsmate/dino/provider/base.py
opsmate/dino/provider/ollama.py
opsmate/dino/provider/openai.py
opsmate/dino/provider/xai.py
opsmate/gui/app.py
opsmate/gui/assets.py
opsmate/gui/components.py
opsmate/gui/config.py
opsmate/gui/models.py
opsmate/gui/seed.py
opsmate/gui/steps.py
opsmate/gui/views.py
opsmate/ingestions/__init__.py
opsmate/ingestions/base.py
opsmate/ingestions/chunk.py
opsmate/ingestions/fs.py
opsmate/ingestions/github.py
opsmate/ingestions/jobs.py
opsmate/ingestions/models.py
opsmate/knowledgestore/__init__.py
opsmate/knowledgestore/models.py
opsmate/libs/config/__init__.py
opsmate/libs/config/base_settings.py
opsmate/libs/core/trace/__init__.py
opsmate/migrations/README
opsmate/migrations/alembic.ini
opsmate/migrations/env.py
opsmate/migrations/script.py.mako
opsmate/migrations/versions/79fe7d287ba8_init_db_schema.py
opsmate/migrations/versions/b86047adede9_introduce_the_concept_of_named_queue_in_.py
opsmate/plugins/__init__.py
opsmate/plugins/plugins.py
opsmate/polya/__init__.py
opsmate/polya/execution.py
opsmate/polya/models.py
opsmate/polya/planning.py
opsmate/polya/understanding.py
opsmate/runtime/__init__.py
opsmate/runtime/docker.py
opsmate/runtime/k8s.py
opsmate/runtime/local.py
opsmate/runtime/runtime.py
opsmate/runtime/ssh.py
opsmate/tests/__init__.py
opsmate/tests/base.py
opsmate/tests/apiserver/test_apiserver.py
opsmate/tests/cli/test_cli.py
opsmate/tests/core/__init__.py
opsmate-0.2.3a2.dist-info/METADATA
opsmate-0.2.3a2.dist-info/WHEEL
opsmate-0.2.3a2.dist-info/entry_points.txt
opsmate-0.2.3a2.dist-info/licenses/LICENSE
opsmate-0.2.3a2.dist-info/RECORD
