Metadata-Version: 2.4
Name: opsmate
Version: 0.2.3a2
Summary: opsmate is a SRE AI assistant
Author-email: Jingkai <jingkai@hey.com>
License: MIT License
License-File: LICENSE
Requires-Python: <4.0,>=3.10
Requires-Dist: aiohttp!=3.11.13,>=3.11.0
Requires-Dist: alembic<2.0.0,>=1.14.1
Requires-Dist: click<9.0.0,>=8.1.7
Requires-Dist: fastapi[standard]<1.0.0,>=0.115.5
Requires-Dist: graphviz<1.0.0,>=0.20.3
Requires-Dist: html2text==2024.2.26
Requires-Dist: httpx<1.0.0,>=0.27.2
Requires-Dist: instructor[anthropic]<2.0.0,>=1.7.9
Requires-Dist: jinja2<4.0.0,>=3.1.6
Requires-Dist: lancedb==0.20.0
Requires-Dist: matplotlib<4.0.0,>=3.10.1
Requires-Dist: opentelemetry-exporter-otlp>=1.31.0
Requires-Dist: opentelemetry-instrumentation-anthropic>=0.38.12
Requires-Dist: opentelemetry-instrumentation-openai>=0.38.12
Requires-Dist: opentelemetry-instrumentation-sqlalchemy>=0.52b0
Requires-Dist: opentelemetry-instrumentation-starlette>=0.52b0
Requires-Dist: pandas<3.0.0,>=2.2.3
Requires-Dist: pip>=25.0.1
Requires-Dist: plotext<6.0.0,>=5.3.2
Requires-Dist: plotly<7.0.0,>=6.0.0
Requires-Dist: pydantic-settings<3.0.0,>=2.6.1
Requires-Dist: pydantic<3.0.0,>=2.8.2
Requires-Dist: python-fasthtml<1.0.0,>=0.10.0
Requires-Dist: pytz<2026.0,>=2025.1
Requires-Dist: pyyaml<7.0.0,>=6.0.2
Requires-Dist: rich<14.0.0,>=13.8.1
Requires-Dist: setuptools>=76.0.0
Requires-Dist: sqlmodel<1.0.0,>=0.0.22
Requires-Dist: structlog<25.0.0,>=24.4.0
Requires-Dist: tabulate>=0.9.0
Provides-Extra: reranker-answerdotai
Requires-Dist: rerankers[transformers]; extra == 'reranker-answerdotai'
Provides-Extra: reranker-cohere
Requires-Dist: cohere<6.0.0,>=5.14.0; extra == 'reranker-cohere'
Provides-Extra: sentence-transformers
Requires-Dist: sentence-transformers<4.0.0,>=3.4.1; extra == 'sentence-transformers'
